openai2/__init__.py
openai2/_chat.py
openai2/_chat_model.py
openai2/_group_chat.py
openai2-1.7.13.dist-info/entry_points.txt
openai2-1.7.13.dist-info/LICENSE
openai2-1.7.13.dist-info/WHEEL
openai2-1.7.13.dist-info/METADATA
openai2-1.7.13.dist-info/RECORD
