Metadata-Version: 2.1
Name: openai2
Version: 1.7.13
Summary: ChatGPT 工具包，支持多模态对话（gpt-4o）、连续对话、流式对话（逐字显示）、生成图像（DALL·E）、对话存档与载入、对话回滚、对话伪造、轮询 api_key 池、群聊多角色模拟、限制历史消息数量、异步请求。
Keywords: openai,chatgpt,openai2
Author-email: 江南雨上 <lcctoor@outlook.com>
Requires-Python: >=3.12
Classifier: License :: OSI Approved :: Apache Software License
Requires-Dist: openai>=1.59.6
